samstacks/__init__.py
samstacks/aws_utils.py
samstacks/bootstrap.py
samstacks/cli.py
samstacks/constants.py
samstacks/core.py
samstacks/exceptions.py
samstacks/input_utils.py
samstacks/pipeline_models.py
samstacks/presentation.py
samstacks/reporting.py
samstacks/samconfig_manager.py
samstacks/templating.py
samstacks/ui.py
samstacks/validation.py
samstacks/version.py
samstacks-0.8.0.dist-info/METADATA
samstacks-0.8.0.dist-info/WHEEL
samstacks-0.8.0.dist-info/entry_points.txt
samstacks-0.8.0.dist-info/licenses/LICENSE
samstacks-0.8.0.dist-info/RECORD
