Metadata-Version: 2.4
Name: samstacks
Version: 0.8.0
Summary: A YAML driven pipeline of AWS SAM stacks inspired by GitHub Actions.
Project-URL: Homepage, https://dev7a.github.io/samstacks/
Project-URL: Repository, https://github.com/dev7a/samstacks
Project-URL: Issues, https://github.com/dev7a/samstacks/issues
Project-URL: Documentation, https://dev7a.github.io/samstacks/
Author-email: Alessandro Bologna <alessandro.bologna@gmail.com>
License: MIT License
License-File: LICENSE
Keywords: aws,cloudformation,deployment,pipeline,sam,serverless
Classifier: Development Status :: 4 - Beta
Classifier: Intended Audience :: Developers
Classifier: License :: OSI Approved :: MIT License
Classifier: Programming Language :: Python :: 3
Classifier: Programming Language :: Python :: 3.12
Classifier: Topic :: Software Development :: Build Tools
Classifier: Topic :: System :: Systems Administration
Requires-Python: >=3.12
Requires-Dist: boto3>=1.26.0
Requires-Dist: click>=8.0.0
Requires-Dist: pydantic>=2.0.0
Requires-Dist: pyyaml>=6.0
Requires-Dist: rich>=13.0.0
Requires-Dist: simpleeval>=0.9.13
Requires-Dist: termcolor>=2.0.0
Requires-Dist: yaspin>=3.0.0
Provides-Extra: dev
Requires-Dist: boto3-stubs; extra == 'dev'
Requires-Dist: build>=0.10.0; extra == 'dev'
Requires-Dist: mypy>=1.0; extra == 'dev'
Requires-Dist: pre-commit>=3.0; extra == 'dev'
Requires-Dist: pytest-cov>=4.0; extra == 'dev'
Requires-Dist: pytest-mock>=3.0; extra == 'dev'
Requires-Dist: pytest>=7.0; extra == 'dev'
Requires-Dist: ruff>=0.1.0; extra == 'dev'
Requires-Dist: twine>=4.0.0; extra == 'dev'
Requires-Dist: types-pyyaml; extra == 'dev'
